baato/__init__.py
baato/config.py
baato/exceptions.py
baato/main.py
baato/resources/__init__.py
baato/resources/direction.py
baato/resources/map_style.py
baato/resources/near_by_places.py
baato/resources/places.py
baato/resources/reverse_search.py
baato/resources/search.py
baato/resources/validators.py
baato-1.0.1.dist-info/LICENSE
baato-1.0.1.dist-info/METADATA
baato-1.0.1.dist-info/WHEEL
baato-1.0.1.dist-info/top_level.txt
baato-1.0.1.dist-info/RECORD
