Metadata-Version: 2.1
Name: baato
Version: 1.0.1
Summary: Baato API for Python
Home-page: https://github.com/baato/python-client
Author: Kathmandu Living Labs Consult
Author-email: klltech@gmail.com
License: MIT License
Keywords: Baato,Python,DRY
Platform: UNKNOWN
Classifier: Development Status :: 5 - Production/Stable
Classifier: Intended Audience :: Developers
Classifier: Topic :: Scientific/Engineering :: GIS
Classifier: Topic :: Software Development
Classifier: License :: OSI Approved :: MIT License
Classifier: Programming Language :: Python
Classifier: Programming Language :: Python :: 3
Classifier: Programming Language :: Python :: 3.6
Classifier: Programming Language :: Python :: 3.7
Classifier: Programming Language :: Python :: 3.8
Classifier: Programming Language :: Python :: 3.9
Classifier: Programming Language :: Python :: 3.10
Requires-Python: >=3.6
Requires-Dist: requests
Requires-Dist: decorator
Requires-Dist: certifi
